{
  "name": "react-javascript",
  "version": "1.0.0",
  "description": "Basic React template with JavaScript",
  "author": "Sonu Kumar",
  "dependencies": {
    "react": "^18.2.0",
    "react-dom": "^18.2.0",
    "react-scripts": "5.0.1"
  },
  "devDependencies": {
    "@testing-library/jest-dom": "^5.16.5",
    "@testing-library/react": "^14.0.0",
    "@testing-library/user-event": "^14.4.3"
  },
  "files": [
    "src/App.jsx",
    "src/index.jsx",
    "src/App.css",
    "public/index.html",
    "components/Layout.jsx",
    "pages/Home.jsx",
    "utils/api.js"
  ],
  "scripts": {
    "start": "react-scripts start",
    "build": "react-scripts build",
    "test": "react-scripts test",
    "eject": "react-scripts eject"
  }
}